[
  {
    "book": "1 Chronicles",
    "chapter": 2,
    "verse": 35,
    "language_code": "en",
    "language_name": "English",
    "words": [
      {
        "position": 1,
        "surface": "וַ/יִּתֵּ֨ן",
        "phrase": "and gave",
        "literal": "and-he-gave",
        "source": "H5414 (KJV: gave; ESV: gave; NASB: gave)"
      },
      {
        "position": 2,
        "surface": "שֵׁשָׁ֧ן",
        "phrase": "Sheshan",
        "literal": "Sheshan",
        "source": "H8348 (KJV: Sheshan; ESV: Sheshan; NASB: Sheshan)"
      },
      {
        "position": 3,
        "surface": "אֶת",
        "phrase": "his",
        "literal": "[direct-object-marker]",
        "source": "H853 (KJV: -; ESV: -; NASB: -)"
      },
      {
        "position": 4,
        "surface": "בִּתּ֛/וֹ",
        "phrase": "daughter",
        "literal": "daughter-his",
        "source": "H1323 (KJV: his daughter; ESV: his daughter; NASB: his daughter)"
      },
      {
        "position": 5,
        "surface": "לְ/יַרְחָ֥ע",
        "phrase": "to Jarha",
        "literal": "to-Jarha",
        "source": "H3398 (KJV: Jarha; ESV: Jarha; NASB: Jarha)"
      },
      {
        "position": 6,
        "surface": "עַבְדּ֖/וֹ",
        "phrase": "his servant",
        "literal": "servant-his",
        "source": "H5650 (KJV: his servant; ESV: his servant; NASB: his servant)"
      },
      {
        "position": 7,
        "surface": "לְ/אִשָּׁ֑ה",
        "phrase": "as a wife",
        "literal": "to-wife",
        "source": "H802 (KJV: to wife; ESV: in marriage; NASB: as a wife)"
      },
      {
        "position": 8,
        "surface": "וַ/תֵּ֥לֶד",
        "phrase": "and she bore",
        "literal": "and-she-bore",
        "source": "H3205 (KJV: and she bare; ESV: and she bore; NASB: and she bore)"
      },
      {
        "position": 9,
        "surface": "ל֖/וֹ",
        "phrase": "to him",
        "literal": "to-him",
        "source": "- (KJV: him; ESV: him; NASB: him)"
      },
      {
        "position": 10,
        "surface": "אֶת",
        "phrase": "-",
        "literal": "[direct-object-marker]",
        "source": "H853 (KJV: -; ESV: -; NASB: -)"
      },
      {
        "position": 11,
        "surface": "עַתָּֽי",
        "phrase": "Attai",
        "literal": "Attai",
        "source": "H6262 (KJV: Attai; ESV: Attai; NASB: Attai)"
      }
    ]
  }
]
