[
  {
    "book": "1 Samuel",
    "chapter": 25,
    "verse": 27,
    "language_code": "en",
    "language_name": "English",
    "words": [
      {
        "position": 1,
        "surface": "וְ/עַתָּה֙",
        "phrase": "And now",
        "literal": "and-now",
        "source": "H6258 (KJV: And now; ESV: And now; NASB: Now)"
      },
      {
        "position": 2,
        "surface": "הַ/בְּרָכָ֣ה",
        "phrase": "this blessing",
        "literal": "the-blessing",
        "source": "H1293 (KJV: blessing; ESV: present; NASB: gift)"
      },
      {
        "position": 3,
        "surface": "הַ/זֹּ֔את",
        "phrase": "this",
        "literal": "the-this",
        "source": "H2063 (KJV: this; ESV: this; NASB: this)"
      },
      {
        "position": 4,
        "surface": "אֲשֶׁר",
        "phrase": "which",
        "literal": "which",
        "source": "H834 (KJV: which; ESV: that; NASB: which)"
      },
      {
        "position": 5,
        "surface": "הֵבִ֥יא",
        "phrase": "she has brought",
        "literal": "she-brought",
        "source": "H935 (KJV: hath brought; ESV: has brought; NASB: has brought)"
      },
      {
        "position": 6,
        "surface": "שִׁפְחָתְ/ךָ֖",
        "phrase": "your servant",
        "literal": "maidservant-your",
        "source": "H8198 (KJV: handmaid; ESV: servant; NASB: maidservant)"
      },
      {
        "position": 7,
        "surface": "לַֽ/אדֹנִ֑/י",
        "phrase": "to my lord",
        "literal": "to-lord-my",
        "source": "H113 (KJV: my lord; ESV: my lord; NASB: my lord)"
      },
      {
        "position": 8,
        "surface": "וְ/נִתְּנָה֙",
        "phrase": "and let it be given",
        "literal": "and-let-it-be-given",
        "source": "H5414 (KJV: be given; ESV: be given; NASB: be given)"
      },
      {
        "position": 9,
        "surface": "לַ/נְּעָרִ֔ים",
        "phrase": "to the young men",
        "literal": "to-the-young-men",
        "source": "H5288 (KJV: young men; ESV: young men; NASB: young men)"
      },
      {
        "position": 10,
        "surface": "הַ/מִּֽתְהַלְּכִ֖ים",
        "phrase": "who follow",
        "literal": "the-walking",
        "source": "H1980 (KJV: follow; ESV: follow; NASB: accompany)"
      },
      {
        "position": 11,
        "surface": "בְּ/רַגְלֵ֥י",
        "phrase": "at the feet of",
        "literal": "at-feet-of",
        "source": "H7272 (implied in phrase; KJV/ESV/NASB: follow)"
      },
      {
        "position": 12,
        "surface": "אֲדֹנִֽ/י",
        "phrase": "my lord",
        "literal": "lord-my",
        "source": "H113 (KJV: my lord; ESV: my lord; NASB: my lord)"
      }
    ]
  }
]
