[
  {
    "book": "2 Chronicles",
    "chapter": 30,
    "verse": 13,
    "language_code": "en",
    "language_name": "English",
    "words": [
      {
        "position": 1,
        "surface": "וַ/יֵּֽאָסְפ֤וּ",
        "phrase": "and they assembled",
        "literal": "and-they-were-assembled",
        "source": "H622 (KJV: gathered; ESV: assembled; NASB: assembled)"
      },
      {
        "position": 2,
        "surface": "יְרוּשָׁלִַ֨ם֙",
        "phrase": "to Jerusalem",
        "literal": "Jerusalem",
        "source": "H3389 (KJV: Jerusalem; ESV: Jerusalem; NASB: Jerusalem)"
      },
      {
        "position": 3,
        "surface": "עַם",
        "phrase": "people",
        "literal": "people",
        "source": "H5971 (KJV: people; ESV: people; NASB: people)"
      },
      {
        "position": 4,
        "surface": "רָ֔ב",
        "phrase": "a multitude",
        "literal": "much",
        "source": "H7227 (KJV: multitude; ESV: multitude; NASB: great)"
      },
      {
        "position": 5,
        "surface": "לַ/עֲשׂ֛וֹת",
        "phrase": "to keep",
        "literal": "to-do",
        "source": "H6213 (KJV: to keep; ESV: to keep; NASB: to celebrate)"
      },
      {
        "position": 6,
        "surface": "אֶת",
        "phrase": "the",
        "literal": "direct-object-marker",
        "source": "H853 (KJV: [implied]; ESV: [implied]; NASB: [implied])"
      },
      {
        "position": 7,
        "surface": "חַ֥ג",
        "phrase": "Feast",
        "literal": "feast",
        "source": "H2282 (KJV: feast; ESV: Feast; NASB: Feast)"
      },
      {
        "position": 8,
        "surface": "הַ/מַּצּ֖וֹת",
        "phrase": "of Unleavened Bread",
        "literal": "the-unleavened-breads",
        "source": "H4682 (KJV: unleavened bread; ESV: Unleavened Bread; NASB: Unleavened Bread)"
      },
      {
        "position": 9,
        "surface": "בַּ/חֹ֣דֶשׁ",
        "phrase": "in the month",
        "literal": "in-the-month",
        "source": "H2320 (KJV: in the second month; ESV: in the second month; NASB: in the second month)"
      },
      {
        "position": 10,
        "surface": "הַ/שֵּׁנִ֑י",
        "phrase": "second",
        "literal": "the-second",
        "source": "H8145 (KJV: second; ESV: second; NASB: second)"
      },
      {
        "position": 11,
        "surface": "קָהָ֖ל",
        "phrase": "assembly",
        "literal": "assembly",
        "source": "H6951 (KJV: congregation; ESV: assembly; NASB: assembly)"
      },
      {
        "position": 12,
        "surface": "לָ/רֹ֥ב",
        "phrase": "very great",
        "literal": "to-greatness",
        "source": "H7230 (KJV: very great; ESV: very great; NASB: very great)"
      },
      {
        "position": 13,
        "surface": "מְאֹֽד",
        "phrase": "",
        "literal": "exceedingly",
        "source": "H3966 (KJV: exceedingly; ESV: exceedingly; NASB: very)"
      }
    ]
  }
]
