[
  {
    "book": "2 Chronicles",
    "chapter": 34,
    "verse": 17,
    "language_code": "en",
    "language_name": "English",
    "words": [
      {
        "position": 1,
        "surface": "וַ/יַּתִּ֕יכוּ",
        "phrase": "And they poured out",
        "literal": "and-they-poured-out",
        "source": "H5413 (KJV: gathered together; ESV: emptied out; NASB: emptied out)"
      },
      {
        "position": 2,
        "surface": "אֶת",
        "phrase": "[direct object marker]",
        "literal": "[direct object marker]",
        "source": "H853 (KJV: [implied]; ESV: [implied]; NASB: [implied])"
      },
      {
        "position": 3,
        "surface": "הַ/כֶּ֖סֶף",
        "phrase": "the silver",
        "literal": "the-silver",
        "source": "H3701 (KJV: money; ESV: money; NASB: money)"
      },
      {
        "position": 4,
        "surface": "הַ/נִּמְצָ֣א",
        "phrase": "that was found",
        "literal": "the-found",
        "source": "H4672 (KJV: that was found; ESV: that was found; NASB: which was found)"
      },
      {
        "position": 5,
        "surface": "בְּ/בֵית",
        "phrase": "in house",
        "literal": "in-house-of",
        "source": "H1004 (KJV: in the house; ESV: in the house; NASB: in the house)"
      },
      {
        "position": 6,
        "surface": "יְהוָ֑ה",
        "phrase": "YHWH",
        "literal": "YHWH",
        "source": "H3068 (KJV: of the LORD; ESV: of the LORD; NASB: of the LORD)"
      },
      {
        "position": 7,
        "surface": "וַֽ/יִּתְּנ֗וּ/הוּ",
        "phrase": "and they gave it",
        "literal": "and-they-gave-it",
        "source": "H5414 (KJV: have delivered; ESV: have given; NASB: have delivered)"
      },
      {
        "position": 8,
        "surface": "עַל",
        "phrase": "upon",
        "literal": "upon",
        "source": "H5921 (KJV: into; ESV: into; NASB: into)"
      },
      {
        "position": 9,
        "surface": "יַד֙",
        "phrase": "hand of",
        "literal": "hand-of",
        "source": "H3027 (KJV: hand; ESV: hand; NASB: hands)"
      },
      {
        "position": 10,
        "surface": "הַ/מֻּפְקָדִ֔ים",
        "phrase": "the overseers",
        "literal": "the-appointed-ones",
        "source": "H6485 (KJV: overseers; ESV: overseers; NASB: supervisors)"
      },
      {
        "position": 11,
        "surface": "וְ/עַל",
        "phrase": "and upon",
        "literal": "and-upon",
        "source": "H5921 (KJV: and to; ESV: and; NASB: and)"
      },
      {
        "position": 12,
        "surface": "יַ֖ד",
        "phrase": "hand of",
        "literal": "hand-of",
        "source": "H3027 (KJV: hand; ESV: hand; NASB: hands)"
      },
      {
        "position": 13,
        "surface": "עוֹשֵׂ֥י",
        "phrase": "doers of",
        "literal": "doing",
        "source": "H6213 (KJV: workmen; ESV: workmen; NASB: workmen)"
      },
      {
        "position": 14,
        "surface": "הַ/מְּלָאכָֽה",
        "phrase": "the work",
        "literal": "the-work",
        "source": "H4399 (KJV: workmen; ESV: workmen; NASB: workmen)"
      }
    ]
  }
]
