[
  {
    "book": "Deuteronomy",
    "chapter": 4,
    "verse": 41,
    "language_code": "en",
    "language_name": "English",
    "words": [
      {
        "position": 1,
        "surface": "אָ֣ז",
        "phrase": "then",
        "literal": "then",
        "source": "H227; KJV: Then, ESV: Then, NASB: Then"
      },
      {
        "position": 2,
        "surface": "יַבְדִּ֤יל",
        "phrase": "set apart",
        "literal": "he-separated",
        "source": "H914; KJV: severed, ESV: set apart, NASB: set apart"
      },
      {
        "position": 3,
        "surface": "מֹשֶׁה֙",
        "phrase": "Moses",
        "literal": "Moses",
        "source": "H4872; KJV: Moses, ESV: Moses, NASB: Moses"
      },
      {
        "position": 4,
        "surface": "שָׁלֹ֣שׁ",
        "phrase": "three",
        "literal": "three",
        "source": "H7969; KJV: three, ESV: three, NASB: three"
      },
      {
        "position": 5,
        "surface": "עָרִ֔ים",
        "phrase": "cities",
        "literal": "cities",
        "source": "H5892; KJV: cities, ESV: cities, NASB: cities"
      },
      {
        "position": 6,
        "surface": "בְּ/עֵ֖בֶר",
        "phrase": "on the other side of",
        "literal": "in/beyond",
        "source": "H5676; KJV: on this side, ESV: on the other side, NASB: on the other side"
      },
      {
        "position": 7,
        "surface": "הַ/יַּרְדֵּ֑ן",
        "phrase": "the Jordan",
        "literal": "the/Jordan",
        "source": "H3383; KJV: Jordan, ESV: the Jordan, NASB: the Jordan"
      },
      {
        "position": 8,
        "surface": "מִזְרְחָ֖/ה",
        "phrase": "eastward",
        "literal": "rising-of/her",
        "source": "H4217; KJV: toward the sunrising, ESV: toward the sunrise, NASB: toward the sunrising"
      },
      {
        "position": 9,
        "surface": "שָֽׁמֶשׁ",
        "phrase": "sun",
        "literal": "sun",
        "source": "H8121; KJV: sun, ESV: sun, NASB: sun"
      }
    ]
  }
]
