[
  {
    "book": "Deuteronomy",
    "chapter": 32,
    "verse": 21,
    "language_code": "en",
    "language_name": "English",
    "words": [
      {
        "position": 1,
        "surface": "הֵ֚ם",
        "phrase": "They",
        "literal": "they",
        "source": "H1992; KJV: They, ESV: They, NASB: They"
      },
      {
        "position": 2,
        "surface": "קִנְא֣וּ/נִי",
        "phrase": "provoked-me-to-jealousy",
        "literal": "they-provoked-me-to-jealousy",
        "source": "H7065; KJV: moved, ESV: provoked, NASB: provoked"
      },
      {
        "position": 3,
        "surface": "בְ/לֹא",
        "phrase": "with-no",
        "literal": "with-not",
        "source": "H3808; KJV: with no, ESV: with that which is, NASB: with no"
      },
      {
        "position": 4,
        "surface": "אֵ֔ל",
        "phrase": "god",
        "literal": "god",
        "source": "H410; KJV: god, ESV: not God, NASB: god"
      },
      {
        "position": 5,
        "surface": "כִּעֲס֖וּ/נִי",
        "phrase": "provoked-me-to-anger",
        "literal": "they-provoked-me-to-anger",
        "source": "H3707; KJV: provoked, ESV: provoked, NASB: angered"
      },
      {
        "position": 6,
        "surface": "בְּ/הַבְלֵי/הֶ֑ם",
        "phrase": "with-their-vain-idols",
        "literal": "with-vain-things-of-them",
        "source": "H1892; KJV: vanities, ESV: idols, NASB: vain things"
      },
      {
        "position": 7,
        "surface": "וַ/אֲנִי֙",
        "phrase": "and-I",
        "literal": "and-I",
        "source": "H589; KJV: And I, ESV: therefore I, NASB: So I"
      },
      {
        "position": 8,
        "surface": "אַקְנִיאֵ֣/ם",
        "phrase": "will-provoke-them-to-jealousy",
        "literal": "I-will-provoke-them-to-jealousy",
        "source": "H7065; KJV: will move, ESV: will make them jealous, NASB: will provoke them to jealousy"
      },
      {
        "position": 9,
        "surface": "בְּ/לֹא",
        "phrase": "with-no",
        "literal": "with-not",
        "source": "H3808; KJV: with, ESV: with those, NASB: with no"
      },
      {
        "position": 10,
        "surface": "עָ֔ם",
        "phrase": "people",
        "literal": "people",
        "source": "H5971; KJV: people, ESV: people, NASB: people"
      },
      {
        "position": 11,
        "surface": "בְּ/ג֥וֹי",
        "phrase": "with-a-nation",
        "literal": "with-nation",
        "source": "H1471; KJV: nation, ESV: nation, NASB: nation"
      },
      {
        "position": 12,
        "surface": "נָבָ֖ל",
        "phrase": "foolish",
        "literal": "foolish",
        "source": "H5036; KJV: foolish, ESV: foolish, NASB: foolish"
      },
      {
        "position": 13,
        "surface": "אַכְעִיסֵֽ/ם",
        "phrase": "will-provoke-them-to-anger",
        "literal": "I-will-provoke-them-to-anger",
        "source": "H3707; KJV: provoke, ESV: provoke, NASB: provoke"
      }
    ]
  }
]
