[
  {
    "book": "Leviticus",
    "chapter": 8,
    "verse": 19,
    "language_code": "en",
    "language_name": "English",
    "words": [
      {
        "position": 1,
        "surface": "וַ/יִּשְׁחָ֑ט",
        "phrase": "and he slaughtered",
        "literal": "and-he-slaughtered",
        "source": "H7819 (KJV: killed; ESV: killed; NASB: slaughtered)"
      },
      {
        "position": 2,
        "surface": "וַ/יִּזְרֹ֨ק",
        "phrase": "and sprinkled",
        "literal": "and-he-sprinkled",
        "source": "H2236 (KJV: sprinkled; ESV: threw; NASB: sprinkled)"
      },
      {
        "position": 3,
        "surface": "מֹשֶׁ֧ה",
        "phrase": "Moses",
        "literal": "Moses",
        "source": "H4872 (KJV/ESV/NASB: Moses)"
      },
      {
        "position": 4,
        "surface": "אֶת",
        "phrase": "[direct object marker]",
        "literal": "[accusative-marker]",
        "source": "H853 (KJV/ESV/NASB: [implied])"
      },
      {
        "position": 5,
        "surface": "הַ/דָּ֛ם",
        "phrase": "the blood",
        "literal": "the-blood",
        "source": "H1818 (KJV/ESV/NASB: the blood)"
      },
      {
        "position": 6,
        "surface": "עַל",
        "phrase": "on",
        "literal": "upon",
        "source": "H5921 (KJV: upon; ESV: against; NASB: on)"
      },
      {
        "position": 7,
        "surface": "הַ/מִּזְבֵּ֖חַ",
        "phrase": "the altar",
        "literal": "the-altar",
        "source": "H4196 (KJV/ESV/NASB: the altar)"
      },
      {
        "position": 8,
        "surface": "סָבִֽיב",
        "phrase": "all around",
        "literal": "around",
        "source": "H5439 (KJV: round about; ESV: sides; NASB: around)"
      }
    ]
  }
]
