[
  {
    "book": "Numbers",
    "chapter": 11,
    "verse": 32,
    "language_code": "en",
    "language_name": "English",
    "words": [
      {
        "position": 1,
        "surface": "וַ/יָּ֣קָם",
        "phrase": "and the people arose",
        "literal": "and-he-arose",
        "source": "H6965 (KJV: stood up; ESV: rose; NASB: spent)"
      },
      {
        "position": 2,
        "surface": "הָ/עָ֡ם",
        "phrase": "the people",
        "literal": "the-people",
        "source": "H5971 (KJV: people; ESV: people; NASB: people)"
      },
      {
        "position": 3,
        "surface": "כָּל",
        "phrase": "all",
        "literal": "all",
        "source": "H3605 (KJV: all; ESV: all; NASB: all)"
      },
      {
        "position": 4,
        "surface": "הַ/יּוֹם֩",
        "phrase": "that day",
        "literal": "the-day",
        "source": "H3117 (KJV: that day; ESV: that day; NASB: day)"
      },
      {
        "position": 5,
        "surface": "הַ/ה֨וּא",
        "phrase": "that",
        "literal": "the-that",
        "source": "H1931 (KJV: that; ESV: that; NASB: that)"
      },
      {
        "position": 6,
        "surface": "וְ/כָל",
        "phrase": "and all",
        "literal": "and-all",
        "source": "H3605 (KJV: all; ESV: all; NASB: all)"
      },
      {
        "position": 7,
        "surface": "הַ/לַּ֜יְלָה",
        "phrase": "the night",
        "literal": "the-night",
        "source": "H3915 (KJV: night; ESV: night; NASB: night)"
      },
      {
        "position": 8,
        "surface": "וְ/כֹ֣ל",
        "phrase": "and all",
        "literal": "and-all",
        "source": "H3605 (KJV: all; ESV: all; NASB: all)"
      },
      {
        "position": 9,
        "surface": "י֣וֹם",
        "phrase": "day",
        "literal": "day",
        "source": "H3117 (KJV: day; ESV: day; NASB: day)"
      },
      {
        "position": 10,
        "surface": "הַֽ/מָּחֳרָ֗ת",
        "phrase": "the next",
        "literal": "the-morrow",
        "source": "H4283 (KJV: next; ESV: next; NASB: next)"
      },
      {
        "position": 11,
        "surface": "וַ/יַּֽאַסְפוּ֙",
        "phrase": "and they gathered",
        "literal": "and-they-gathered",
        "source": "H622 (KJV: gathered; ESV: gathered; NASB: gathered)"
      },
      {
        "position": 12,
        "surface": "אֶת",
        "phrase": "[direct object marker]",
        "literal": "[accusative]",
        "source": "H853 (KJV: [implied]; ESV: [implied]; NASB: [implied])"
      },
      {
        "position": 13,
        "surface": "הַ/שְּׂלָ֔ו",
        "phrase": "the quail",
        "literal": "the-quail",
        "source": "H7958 (KJV: quails; ESV: quail; NASB: quail)"
      },
      {
        "position": 14,
        "surface": "הַ/מַּמְעִ֕יט",
        "phrase": "the least",
        "literal": "the-one-bringing-few",
        "source": "H4591 (KJV: least; ESV: least; NASB: least)"
      },
      {
        "position": 15,
        "surface": "אָסַ֖ף",
        "phrase": "gathered",
        "literal": "gathering",
        "source": "H622 (KJV: gathered; ESV: gathered; NASB: gathered)"
      },
      {
        "position": 16,
        "surface": "עֲשָׂרָ֣ה",
        "phrase": "ten",
        "literal": "ten",
        "source": "H6235 (KJV: ten; ESV: ten; NASB: ten)"
      },
      {
        "position": 17,
        "surface": "חֳמָרִ֑ים",
        "phrase": "homers",
        "literal": "homers",
        "source": "H2563 (KJV: homers; ESV: homers; NASB: homers)"
      },
      {
        "position": 18,
        "surface": "וַ/יִּשְׁטְח֤וּ",
        "phrase": "and they spread",
        "literal": "and-they-spread-out",
        "source": "H7849 (KJV: spread; ESV: spread; NASB: spread)"
      },
      {
        "position": 19,
        "surface": "לָ/הֶם֙",
        "phrase": "for themselves",
        "literal": "to-them",
        "source": " (KJV: for themselves; ESV: for themselves; NASB: for themselves)"
      },
      {
        "position": 20,
        "surface": "שָׁט֔וֹחַ",
        "phrase": "spread out",
        "literal": "spread-out",
        "source": "H7849 (KJV: abroad; ESV: out; NASB: out)"
      },
      {
        "position": 21,
        "surface": "סְבִיב֖וֹת",
        "phrase": "around",
        "literal": "surroundings",
        "source": "H5439 (KJV: round about; ESV: around; NASB: around)"
      },
      {
        "position": 22,
        "surface": "הַֽ/מַּחֲנֶֽה",
        "phrase": "the camp",
        "literal": "the-camp",
        "source": "H4264 (KJV: camp; ESV: camp; NASB: camp)"
      }
    ]
  }
]
