[
  {
    "book": "Numbers",
    "chapter": 26,
    "verse": 48,
    "language_code": "en",
    "language_name": "English",
    "words": [
      {
        "position": 1,
        "surface": "בְּנֵ֤י",
        "phrase": "sons of",
        "literal": "sons-of",
        "source": "H1121 (KJV: sons; ESV: sons; NASB: sons)"
      },
      {
        "position": 2,
        "surface": "נַפְתָּלִי֙",
        "phrase": "Naphtali",
        "literal": "Naphtali",
        "source": "H5321 (KJV: Naphtali; ESV: Naphtali; NASB: Naphtali)"
      },
      {
        "position": 3,
        "surface": "לְ/מִשְׁפְּחֹתָ֔/ם",
        "phrase": "according to their families",
        "literal": "to-families-of-them",
        "source": "H4940 (KJV: families; ESV: clans; NASB: families)"
      },
      {
        "position": 4,
        "surface": "לְ/יַ֨חְצְאֵ֔ל",
        "phrase": "of Jahzeel",
        "literal": "to-Jahzeel",
        "source": "H3183 (KJV: Jahzeel; ESV: Jahzeel; NASB: Jahzeel)"
      },
      {
        "position": 5,
        "surface": "מִשְׁפַּ֖חַת",
        "phrase": "the family",
        "literal": "family",
        "source": "H4940 (KJV: family; ESV: clan; NASB: family)"
      },
      {
        "position": 6,
        "surface": "הַ/יַּחְצְאֵלִ֑י",
        "phrase": "of the Jahzeelites",
        "literal": "the-Jahzeelite",
        "source": "H3184 (KJV: Jahzeelites; ESV: Jahzeelites; NASB: Jahzeelites)"
      },
      {
        "position": 7,
        "surface": "לְ/גוּנִ֕י",
        "phrase": "of Guni",
        "literal": "to-Guni",
        "source": "H1476 (KJV: Guni; ESV: Guni; NASB: Guni)"
      },
      {
        "position": 8,
        "surface": "מִשְׁפַּ֖חַת",
        "phrase": "the family",
        "literal": "family",
        "source": "H4940 (KJV: family; ESV: clan; NASB: family)"
      },
      {
        "position": 9,
        "surface": "הַ/גּוּנִֽי",
        "phrase": "of the Gunites",
        "literal": "the-Gunite",
        "source": "H1477 (KJV: Gunites; ESV: Gunites; NASB: Gunites)"
      }
    ]
  }
]
