[
  {
    "book": "Numbers",
    "chapter": 15,
    "verse": 41,
    "language_code": "en",
    "language_name": "English",
    "words": [
      {
        "position": 1,
        "surface": "אֲנִ֞י",
        "phrase": "I",
        "literal": "I",
        "source": "H589; KJV/ESV/NASB: 'I am'"
      },
      {
        "position": 2,
        "surface": "יְהוָ֣ה",
        "phrase": "YHWH",
        "literal": "YHWH",
        "source": "H3068; KJV/ESV/NASB: 'the LORD'"
      },
      {
        "position": 3,
        "surface": "אֱלֹֽהֵי/כֶ֗ם",
        "phrase": "your God",
        "literal": "God-of-you(pl)",
        "source": "H430; KJV/ESV/NASB: 'your God'"
      },
      {
        "position": 4,
        "surface": "אֲשֶׁ֨ר",
        "phrase": "who",
        "literal": "who/which/that",
        "source": "H834; KJV/ESV/NASB: 'which/who'"
      },
      {
        "position": 5,
        "surface": "הוֹצֵ֤אתִי",
        "phrase": "brought out",
        "literal": "I-caused-to-go-out",
        "source": "H3318; KJV: 'brought', ESV/NASB: 'brought'"
      },
      {
        "position": 6,
        "surface": "אֶתְ/כֶם֙",
        "phrase": "you",
        "literal": "direct-object-you(pl)",
        "source": "H853; KJV/ESV/NASB: 'you'"
      },
      {
        "position": 7,
        "surface": "מֵ/אֶ֣רֶץ",
        "phrase": "from land",
        "literal": "from-land",
        "source": "H776; KJV/ESV/NASB: 'land'"
      },
      {
        "position": 8,
        "surface": "מִצְרַ֔יִם",
        "phrase": "Egypt",
        "literal": "Egypt",
        "source": "H4714; KJV/ESV/NASB: 'Egypt'"
      },
      {
        "position": 9,
        "surface": "לִ/הְי֥וֹת",
        "phrase": "to be",
        "literal": "to-be",
        "source": "H1961; KJV/ESV/NASB: 'to be'"
      },
      {
        "position": 10,
        "surface": "לָ/כֶ֖ם",
        "phrase": "for you",
        "literal": "to-you(pl)",
        "source": "''; KJV/ESV/NASB: 'your'"
      },
      {
        "position": 11,
        "surface": "לֵ/אלֹהִ֑ים",
        "phrase": "for God",
        "literal": "to-God",
        "source": "H430; KJV/ESV/NASB: 'God'"
      },
      {
        "position": 12,
        "surface": "אֲנִ֖י",
        "phrase": "I",
        "literal": "I",
        "source": "H589; KJV/ESV/NASB: 'I am'"
      },
      {
        "position": 13,
        "surface": "יְהוָ֥ה",
        "phrase": "YHWH",
        "literal": "YHWH",
        "source": "H3068; KJV/ESV/NASB: 'the LORD'"
      },
      {
        "position": 14,
        "surface": "אֱלֹהֵי/כֶֽם",
        "phrase": "your God",
        "literal": "God-of-you(pl)",
        "source": "H430; KJV/ESV/NASB: 'your God'"
      }
    ]
  }
]
