[
  {
    "book": "Numbers",
    "chapter": 7,
    "verse": 18,
    "language_code": "en",
    "language_name": "English",
    "words": [
      {
        "position": 1,
        "surface": "בַּ/יּוֹם֙",
        "phrase": "On the day",
        "literal": "in/on-the-day",
        "source": "H3117 (KJV: On the second day; ESV: On the second day; NASB: On the second day)"
      },
      {
        "position": 2,
        "surface": "הַ/שֵּׁנִ֔י",
        "phrase": "the second",
        "literal": "the-second",
        "source": "H8145 (KJV: the second day; ESV: the second day; NASB: the second day)"
      },
      {
        "position": 3,
        "surface": "הִקְרִ֖יב",
        "phrase": "presented",
        "literal": "he-caused-to-approach",
        "source": "H7126 (KJV: offered; ESV: presented; NASB: presented)"
      },
      {
        "position": 4,
        "surface": "נְתַנְאֵ֣ל",
        "phrase": "Nethanel",
        "literal": "Nethanel",
        "source": "H5417 (KJV: Nethaneel; ESV: Nethanel; NASB: Nethanel)"
      },
      {
        "position": 5,
        "surface": "בֶּן",
        "phrase": "son of",
        "literal": "son-of",
        "source": "H1121 (KJV: son of; ESV: son of; NASB: son of)"
      },
      {
        "position": 6,
        "surface": "צוּעָ֑ר",
        "phrase": "Zuar",
        "literal": "Zuar",
        "source": "H6686 (KJV: Zuar; ESV: Zuar; NASB: Zuar)"
      },
      {
        "position": 7,
        "surface": "נְשִׂ֖יא",
        "phrase": "leader of",
        "literal": "prince-of",
        "source": "H5387 (KJV: prince; ESV: leader; NASB: leader)"
      },
      {
        "position": 8,
        "surface": "יִשָּׂשכָֽר",
        "phrase": "Issachar",
        "literal": "Issachar",
        "source": "H3485 (KJV: Issachar; ESV: Issachar; NASB: Issachar)"
      }
    ]
  }
]
